ai/backend/helpers/__init__.py
ai/backend/helpers/display.py
ai/backend/helpers/package.py
ai/backend/kernel/__init__.py
ai/backend/kernel/__main__.py
ai/backend/kernel/base.py
ai/backend/kernel/logging.py
ai/backend/kernel/terminal.py
ai/backend/kernel/test_utils.py
ai/backend/kernel/utils.py
ai/backend/kernel/c/__init__.py
ai/backend/kernel/cpp/__init__.py
ai/backend/kernel/git/__init__.py
ai/backend/kernel/golang/__init__.py
ai/backend/kernel/haskell/__init__.py
ai/backend/kernel/java/__init__.py
ai/backend/kernel/julia/__init__.py
ai/backend/kernel/lua/__init__.py
ai/backend/kernel/nodejs/__init__.py
ai/backend/kernel/octave/__init__.py
ai/backend/kernel/php/__init__.py
ai/backend/kernel/python/__init__.py
ai/backend/kernel/python/inproc.py
ai/backend/kernel/python/types.py
ai/backend/kernel/python/display/__init__.py
ai/backend/kernel/python/drawing/__init__.py
ai/backend/kernel/python/drawing/canvas.py
ai/backend/kernel/python/drawing/color.py
ai/backend/kernel/python/drawing/encoding.py
ai/backend/kernel/python/drawing/turtle.py
ai/backend/kernel/python/matplotlib/__init__.py
ai/backend/kernel/python/matplotlib/ingen.py
ai/backend/kernel/r/__init__.py
ai/backend/kernel/r_server_ms/__init__.py
ai/backend/kernel/rust/__init__.py
ai/backend/kernel/scheme/__init__.py
ai/backend/kernel/vendor/__init__.py
ai/backend/kernel/vendor/aws_polly/__init__.py
ai/backend/kernel/vendor/aws_polly/inproc.py
backend.ai_kernel_runner-1.4.2.dist-info/METADATA
backend.ai_kernel_runner-1.4.2.dist-info/RECORD
backend.ai_kernel_runner-1.4.2.dist-info/WHEEL
backend.ai_kernel_runner-1.4.2.dist-info/top_level.txt
