Metadata-Version: 2.1
Name: backend.ai-kernel-runner
Version: 1.4.2
Summary: User code executors for Backend.AI kernels
Home-page: https://github.com/lablup/backend.ai-kernel-runner
Author: Lablup Inc.
Author-email: joongi@lablup.com
License: MIT
Platform: UNKNOWN
Classifier: License :: OSI Approved :: MIT License
Classifier: Intended Audience :: Developers
Classifier: Programming Language :: Python
Classifier: Programming Language :: Python :: 3
Classifier: Programming Language :: Python :: 3.6
Classifier: Operating System :: POSIX
Classifier: Operating System :: MacOS :: MacOS X
Classifier: Environment :: No Input/Output (Daemon)
Classifier: Topic :: Scientific/Engineering
Classifier: Topic :: Software Development
Requires-Python: >=3.6
Provides-Extra: golang
Provides-Extra: rust
Provides-Extra: lua
Provides-Extra: cpp
Provides-Extra: git
Provides-Extra: test
Provides-Extra: nodejs
Provides-Extra: ci
Provides-Extra: php
Provides-Extra: c
Provides-Extra: haskell
Provides-Extra: dev
Provides-Extra: r
Provides-Extra: r_server_ms
Provides-Extra: python
Provides-Extra: build
Provides-Extra: julia
Provides-Extra: vendor.aws_polly
Provides-Extra: scheme
Provides-Extra: octave
Provides-Extra: java
Requires-Dist: async-timeout (~=3.0)
Requires-Dist: pyzmq (~=17.0)
Requires-Dist: uvloop (~=0.11.0)
Requires-Dist: attrs (>=18.0)
Requires-Dist: namedlist
Requires-Dist: janus (>=0.3.0)
Requires-Dist: msgpack (~=0.5.6)
Provides-Extra: build
Requires-Dist: wheel (>=0.31.0); extra == 'build'
Requires-Dist: twine (>=1.11.0); extra == 'build'
Provides-Extra: c
Provides-Extra: ci
Provides-Extra: cpp
Provides-Extra: dev
Requires-Dist: wheel (>=0.31.0); extra == 'dev'
Requires-Dist: twine (>=1.11.0); extra == 'dev'
Requires-Dist: pytest (~=3.7.0); extra == 'dev'
Requires-Dist: pytest-asyncio (>=0.8.0); extra == 'dev'
Requires-Dist: pytest-cov; extra == 'dev'
Requires-Dist: pytest-mock; extra == 'dev'
Requires-Dist: asynctest; extra == 'dev'
Requires-Dist: flake8; extra == 'dev'
Requires-Dist: codecov; extra == 'dev'
Requires-Dist: pytest-sugar (>=0.9.1); extra == 'dev'
Provides-Extra: git
Provides-Extra: golang
Provides-Extra: haskell
Provides-Extra: java
Provides-Extra: julia
Provides-Extra: lua
Provides-Extra: nodejs
Provides-Extra: octave
Provides-Extra: php
Provides-Extra: python
Requires-Dist: six; extra == 'python'
Requires-Dist: IPython; extra == 'python'
Requires-Dist: pandas; extra == 'python'
Requires-Dist: numpy; extra == 'python'
Requires-Dist: matplotlib; extra == 'python'
Requires-Dist: msgpack; extra == 'python'
Provides-Extra: r
Provides-Extra: r_server_ms
Requires-Dist: aiohttp; extra == 'r_server_ms'
Requires-Dist: yarl; extra == 'r_server_ms'
Provides-Extra: rust
Provides-Extra: scheme
Provides-Extra: test
Requires-Dist: pytest (~=3.7.0); extra == 'test'
Requires-Dist: pytest-asyncio (>=0.8.0); extra == 'test'
Requires-Dist: pytest-cov; extra == 'test'
Requires-Dist: pytest-mock; extra == 'test'
Requires-Dist: asynctest; extra == 'test'
Requires-Dist: flake8; extra == 'test'
Requires-Dist: codecov; extra == 'test'
Provides-Extra: vendor.aws_polly
Requires-Dist: boto3 (~=1.6.23); extra == 'vendor.aws_polly'
Requires-Dist: botocore (~=1.9.23); extra == 'vendor.aws_polly'
